{
  "unevaluatedProperties" : false,
  "properties" : {
    "soqlToExecute" : {
      "title" : "SOQL To Execute",
      "description" : "Ready-to-execute SOQL query",
      "lightning:type" : "lightning__textType",
      "lightning:isPII" : false,
      "copilotAction:isUserInput" : false
    },
    "contextToCreateSoql" : {
      "title" : "Context To Create SOQL",
      "description" : "Natural language description for SOQL generation",
      "lightning:type" : "lightning__textType",
      "lightning:isPII" : false,
      "copilotAction:isUserInput" : false
    },
    "promptToCreateSoql" : {
      "title" : "Prompt Template For SOQL Creation",
      "description" : "Name of the prompt template to use for SOQL generation",
      "lightning:type" : "lightning__textType",
      "lightning:isPII" : false,
      "copilotAction:isUserInput" : false
    }
  },
  "lightning:type" : "lightning__objectType"
}